llama_index/llms/oci_data_science/__init__.py
llama_index/llms/oci_data_science/base.py
llama_index/llms/oci_data_science/client.py
llama_index/llms/oci_data_science/utils.py
llama_index_llms_oci_data_science-0.3.1.dist-info/METADATA
llama_index_llms_oci_data_science-0.3.1.dist-info/WHEEL
llama_index_llms_oci_data_science-0.3.1.dist-info/licenses/LICENSE
llama_index_llms_oci_data_science-0.3.1.dist-info/RECORD
