Metadata-Version: 2.4
Name: llama-index-llms-oci-data-science
Version: 0.3.1
Summary: llama-index llms OCI Data Science integration
Author-email: Dmitrii Cherkasov <dmitrii.cherkasov@oracle.com>
License-Expression: MIT
License-File: LICENSE
Requires-Python: <4.0,>=3.9
Requires-Dist: llama-index-core<0.15,>=0.13.0
Requires-Dist: oci>=2.150.2
